{
    "Abraham Moss": "ABM",
    "Altrincham": "ALT",
    "Anchorage": "ANC",
    "Ashton Moss": "ASM",
    "Ashton West": "ASW",
    "Ashton-Under-Lyne": "ASH",
    "Audenshaw": "AUD",
    "Baguley": "BAG",
    "Barlow Moor Road": "BMR",
    "Barton Dock Road": "EVC",
    "Benchill": "BCH",
    "Besses O' Th' Barn": "BOB",
    "Bowker Vale": "BKV",
    "Broadway": "BDW",
    "Brooklands": "BRK",
    "Burton Road": "BRT",
    "Bury": "BRY",
    "Cemetery Road": "CER",
    "Central Park": "CEP",
    "Chorlton": "CHO",
    "Clayton Hall": "CLA",
    "Cornbrook": "CNK",
    "Crossacres": "CRO",
    "Crumpsall": "CRP",
    "Dane Road": "DAN",
    "Deansgate - Castlefield": "GMX",
    "Derker": "DER",
    "Didsbury Village": "DDV",
    "Droylsden": "DYL",
    "East Didsbury": "EDD",
    "Eccles": "ECC",
    "Edge Lane": "EDL",
    "Etihad Campus": "SPC",
    "Exchange Quay": "EXQ",
    "Exchange Square": "EXS",
    "Failsworth": "FAL",
    "Firswood": "FIR",
    "Freehold": "FRE",
    "Harbour City": "HBC",
    "Heaton Park": "HPK",
    "Hollinwood": "HOL",
    "Holt Town": "HOT",
    "Imperial War Museum": "IWM",
    "Kingsway Business Park": "KIN",
    "Ladywell": "LDW",
    "Langworthy": "LGW",
    "Manchester Airport": "AIR",
    "Market Street": "MKT",
    "Martinscroft": "MAR",
    "MediaCityUK": "MEC",
    "Milnrow": "MIL",
    "Monsall": "MON",
    "Moor Road": "MRD",
    "Navigation Road": "NAV",
    "New Islington": "NIS",
    "Newbold": "NEB",
    "Newhey": "NEH",
    "Newton Heath and Moston": "NHM",
    "Northern Moor": "NMR",
    "Old Trafford": "OLD",
    "Oldham Central": "OHC",
    "Oldham King Street": "OHK",
    "Oldham Mumps": "OHM",
    "Parkway": "PAR",
    "Peel Hall": "PLH",
    "Piccadilly": "PIC",
    "Piccadilly Gardens": "PCG",
    "Pomona": "POM",
    "Prestwich": "PRS",
    "Queens Road": "QNS",
    "Radcliffe": "RAD",
    "Robinswood Road": "RBN",
    "Rochdale Railway Station": "ROC",
    "Rochdale Town Centre": "RTC",
    "Roundthorn": "RTH",
    "Sale": "SAL",
    "Sale Water Park": "SWP",
    "Salford Quays": "SFQ",
    "Shadowmoss": "SHD",
    "Shaw and Crompton": "SHC",
    "Shudehill": "SHL",
    "South Chadderton": "SOC",
    "St Peter's Square": "SPS",
    "St Werburgh's Road": "SWR",
    "Stretford": "STR",
    "The Trafford Centre": "TRC",
    "Timperley": "TMP",
    "Trafford Bar": "TFB",
    "Velopark": "VEL",
    "Victoria": "VIC",
    "Village": "VLG",
    "Weaste": "WST",
    "West Didsbury": "WDD",
    "Westwood": "WWD",
    "Wharfside": "WSD",
    "Whitefield": "WFD",
    "Withington": "WTH",
    "Wythenshawe Park": "WPK",
    "Wythenshawe Town Centre": "WYC"
}